MANIFEST.in
README
dqn.py
setup.cfg
setup.py
dqn.egg-info/PKG-INFO
dqn.egg-info/SOURCES.txt
dqn.egg-info/dependency_links.txt
dqn.egg-info/entry_points.txt
dqn.egg-info/not-zip-safe
dqn.egg-info/requires.txt
dqn.egg-info/top_level.txt